usercustomize.cpython-312-darwin.so
cms_enhance/core.cpython-312-darwin.so
happy_cms-2025082001.dist-info/METADATA
happy_cms-2025082001.dist-info/WHEEL
happy_cms-2025082001.dist-info/top_level.txt
happy_cms-2025082001.dist-info/RECORD
