Metadata-Version: 2.4
Name: happy-cms
Version: 2025082001
Summary: CMS Enhanced Module (Compiled Binary Only - No Source Code)
Home-page: https://github.com/iLay1678/cloud-media-sync-enhanced
Author: iLay1678
Author-email: iLay1678 <your.email@example.com>
License: MIT
Project-URL: Homepage, https://github.com/iLay1678/happy_cms
Project-URL: Repository, https://github.com/iLay1678/happy_cms.git
Project-URL: Issues, https://github.com/iLay1678/happy_cms/issues
Keywords: cms,enhancement,compiled,binary
Classifier: Development Status :: 4 - Beta
Classifier: Intended Audience :: Developers
Classifier: License :: OSI Approved :: MIT License
Classifier: Programming Language :: Python :: 3
Classifier: Programming Language :: Python :: 3.12
Classifier: Programming Language :: Cython
Classifier: Topic :: Software Development :: Libraries :: Python Modules
Requires-Python: >=3.12
Requires-Dist: python-dotenv>=1.1.0
Requires-Dist: nullbr>=1.0.0
Requires-Dist: blacksheep>=2.4.0
Requires-Dist: pytelegrambotapi>=4.28.0
Requires-Dist: uvicorn>=0.35.0
Provides-Extra: dev
Requires-Dist: cython>=3.0.12; extra == "dev"
Requires-Dist: setuptools>=78.1.0; extra == "dev"
Requires-Dist: wheel; extra == "dev"
Requires-Dist: twine; extra == "dev"
Requires-Dist: build; extra == "dev"
Dynamic: author
Dynamic: home-page
Dynamic: requires-python
